delta2k/__init__.py
delta2k/source.py
delta2k/x_deltaMethod.py
delta2k/x_deltaMethod2.py
delta2k/x_plots.py
delta2k/data/Delta2kQuickStart.ipynb
delta2k/data/YRCuster2012.txt
delta2k-0.0.7.dist-info/LICENSE
delta2k-0.0.7.dist-info/METADATA
delta2k-0.0.7.dist-info/WHEEL
delta2k-0.0.7.dist-info/top_level.txt
delta2k-0.0.7.dist-info/RECORD
