Metadata-Version: 2.1
Name: delta2k
Version: 0.0.7
Summary: First delta2k distribution package.
Home-page: https://github.com/pypa/sampleproject
Author: Gregory Coyle
Author-email: gregory.coyle@tufts.edu
License: UNKNOWN
Platform: UNKNOWN
Classifier: Programming Language :: Python :: 3
Classifier: License :: OSI Approved :: MIT License
Classifier: Operating System :: OS Independent
Requires-Python: >=3.6
Requires-Dist: pandas (>=1.0.3)
Requires-Dist: astroplan
Requires-Dist: scipy (>=1.5.0)
Requires-Dist: bokeh (>=2.1.1)
Requires-Dist: jupyterlab (>=2.1.5)
